swg2pyt/Asserter.py
swg2pyt/CaseCollector.py
swg2pyt/ClassGenerator.py
swg2pyt/Executor.py
swg2pyt/GlobalDict.py
swg2pyt/Pretreator.py
swg2pyt/__init__.py
swg2pyt/pytest_swg2pyt/__init__.py
swg2pyt/pytest_swg2pyt/pytest_conftest.py
swg2pyt-0.2.9.dist-info/LICENSE
swg2pyt-0.2.9.dist-info/METADATA
swg2pyt-0.2.9.dist-info/WHEEL
swg2pyt-0.2.9.dist-info/entry_points.txt
swg2pyt-0.2.9.dist-info/top_level.txt
swg2pyt-0.2.9.dist-info/RECORD
