Metadata-Version: 2.1
Name: swg2pyt
Version: 0.2.9
Summary: A helper generate swagger_client code to pytest format
Home-page: 
Author: walkzombie
Author-email: walkzombie@163.com
Classifier: Programming Language :: Python :: 3
Classifier: License :: Freeware
Classifier: Operating System :: Microsoft :: Windows
Classifier: Framework :: Pytest
Requires-Python: >=3.4
License-File: LICENSE
